.editorconfig
.gitignore
.gitlab-ci.yml
LICENSE
README.rst
publish.settings.sh
publish.sh
pyproject.toml
rtfd_requirements.txt
.idea/modules.xml
.idea/peek-office-doc.iml
.idea/inspectionProfiles/Project_Default.xml
.idea/inspectionProfiles/profiles_settings.xml
peek_office_doc/PlatformDependencyTest.py
peek_office_doc/__init__.py
peek_office_doc/build_html_docs.sh
peek_office_doc/build_pdf_doc.sh
peek_office_doc/conf.py
peek_office_doc/index.rst
peek_office_doc/watch_docs.sh
peek_office_doc/welcome.rst
peek_office_doc.egg-info/PKG-INFO
peek_office_doc.egg-info/SOURCES.txt
peek_office_doc.egg-info/dependency_links.txt
peek_office_doc.egg-info/requires.txt
peek_office_doc.egg-info/top_level.txt
peek_office_doc/_static/.gitkeep
peek_office_doc/_static/fonts/fontawesome-webfont.woff2