Metadata-Version: 2.4
Name: peek-office-doc
Version: 5.0.4
Summary: Peek Developer Documentation - the user documentation container for Peek Office
Author-email: Synerty <contact@synerty.com>
Project-URL: Homepage, https://github.com/Synerty/peek-office-doc
Keywords: Peek,Python,Platform,synerty
License-File: LICENSE
Requires-Dist: peek_plugin_base==5.0.4
Requires-Dist: sphinx
Requires-Dist: sphinx-autobuild
Dynamic: license-file
